a2a_json_rpc/__init__.py
a2a_json_rpc/a2a_error_codes.py
a2a_json_rpc/a2a_errors.py
a2a_json_rpc/a2a_spec.json
a2a_json_rpc/json_rpc_error_codes.py
a2a_json_rpc/json_rpc_errors.py
a2a_json_rpc/models.py
a2a_json_rpc/protocol.py
a2a_json_rpc/spec.py
a2a_json_rpc/transport.py
a2a_json_rpc-0.3.0.dist-info/licenses/LICENSE.md
a2a_json_rpc-0.3.0.dist-info/METADATA
a2a_json_rpc-0.3.0.dist-info/WHEEL
a2a_json_rpc-0.3.0.dist-info/top_level.txt
a2a_json_rpc-0.3.0.dist-info/RECORD
