Metadata-Version: 2.4
Name: a2a-json-rpc
Version: 0.3.0
Summary: JSON-RPC implementation for the A2A (Agent-to-Agent) Protocol
Author-email: Chris Hay <chrishayuk@example.com>
License: MIT
Classifier: Development Status :: 4 - Beta
Classifier: Intended Audience :: Developers
Classifier: License :: OSI Approved :: MIT License
Classifier: Programming Language :: Python :: 3
Classifier: Programming Language :: Python :: 3.11
Classifier: Topic :: Software Development :: Libraries
Requires-Python: >=3.11
License-File: LICENSE.md
Requires-Dist: anyio>=4.9.0
Requires-Dist: pydantic>=2.11.3
Provides-Extra: dev
Requires-Dist: pytest>=8.3.5; extra == "dev"
Requires-Dist: pytest-asyncio>=0.23.0; extra == "dev"
Requires-Dist: pytest-cov>=4.1.0; extra == "dev"
Dynamic: license-file
